py_irsend/__init__.py
py_irsend/irsend.py
py_irsend-1.0.2.dist-info/LICENSE
py_irsend-1.0.2.dist-info/METADATA
py_irsend-1.0.2.dist-info/WHEEL
py_irsend-1.0.2.dist-info/top_level.txt
py_irsend-1.0.2.dist-info/RECORD
