Metadata-Version: 2.1
Name: py-irsend
Version: 1.0.2
Summary: A simple wrapper for lirc's irsend. 
Home-page: https://github.com/ChristopherRogers1991/python-irsend
Author: Christopher Rogers
Author-email: ChristopherRogers1991@gmail.com
License: GPLv3
Keywords: lirc irsend
Platform: UNKNOWN
Classifier: Development Status :: 4 - Beta
Classifier: Intended Audience :: Developers
Classifier: Topic :: Software Development :: Libraries :: Python Modules
Classifier: License :: OSI Approved :: GNU General Public License v3 (GPLv3)
Classifier: Programming Language :: Python :: 2
Classifier: Programming Language :: Python :: 3
